pypal/__init__.py
pypal/__main__.py
pypal/generator.py
pypal_nyu-0.1.6.dist-info/licenses/LICENSE
pypal_nyu-0.1.6.dist-info/METADATA
pypal_nyu-0.1.6.dist-info/WHEEL
pypal_nyu-0.1.6.dist-info/entry_points.txt
pypal_nyu-0.1.6.dist-info/top_level.txt
pypal_nyu-0.1.6.dist-info/RECORD
