Metadata-Version: 2.4
Name: pypal_nyu
Version: 0.1.6
Summary: A package that generates random address, names, phonenumbers and profile to fulfill website registration requirements.
Author-email: Xiangyu Lin <xl4358@nyu.edu>, Yubei Ni <yn2178@nyu.edu>, Zifan Zhao <zz4330@nyu.edu>, Siyue Gu <sg7510@nyu.edu>
License: MIT License
Project-URL: Homepage, https://github.com/software-students-spring2025/3-python-package-pypal
Project-URL: Repository, https://github.com/software-students-spring2025/3-python-package-pypal.git
Project-URL: Bug Tracker, https://github.com/software-students-spring2025/3-python-package-pypal/issues
Keywords: python,email,name,phone numbers,profile,random,generator
Classifier: Programming Language :: Python :: 3
Classifier: Intended Audience :: Developers
Classifier: License :: OSI Approved :: MIT License
Classifier: Operating System :: OS Independent
Requires-Python: >=3.7
License-File: LICENSE
Provides-Extra: dev
Requires-Dist: pytest; extra == "dev"
Dynamic: license-file
